pygbq/__init__.py
pygbq/pygbq.py
tests/__init__.py
tests/test_pygbq.py
pygbq-0.26.dist-info/LICENSE
pygbq-0.26.dist-info/METADATA
pygbq-0.26.dist-info/WHEEL
pygbq-0.26.dist-info/top_level.txt
pygbq-0.26.dist-info/RECORD
