Metadata-Version: 2.1
Name: pygbq
Version: 0.26
Summary: Easily integrate data in BigQuery
Home-page: https://github.com/ZiggerZZ/pygbq
Author: Zigfrid Zvezdin
Author-email: ziggerzz@gmail.com
License: UNKNOWN
Platform: UNKNOWN
Classifier: Programming Language :: Python :: 3
Classifier: License :: OSI Approved :: MIT License
Classifier: Operating System :: OS Independent
Requires-Python: >=3.6
Requires-Dist: pandas
Requires-Dist: pandas-gbq
Requires-Dist: pytz
Requires-Dist: google-auth
Requires-Dist: google-cloud-bigquery
Requires-Dist: google-cloud-logging
Requires-Dist: google-cloud-secret-manager
Requires-Dist: bigquery-schema-generator
Requires-Dist: tqdm
Requires-Dist: pyarrow
